{
  "EntryIndex": 0,
  "Nodes": [
    {
      "Node": "{ \"TimerAction\" : 0.10000} ",
      "Next": 1,
      "Prallel": -1
    },
    {
      "Node": "{ \"LoadScenesAction\" : \"S0105\", { 0.00000, 0.00000, 0.00000} , { 0.00000, 0.00000, 0.00000} , 0, False, 0, \"In_scene_01.wav\", 0.70000} ",
      "Next": 2,
      "Prallel": -1
    },
    {
      "Node": "{ \"TimerAction\" : 0.10000} ",
      "Next": 21,
      "Prallel": -1
    },
    {
      "Node": "{ \"NpcTransformAction\" : True, { 110.98300, 1.81954, -792.48000} , True, { 0.00000, 103.82610, 0.00000} , \"in0701\"} ",
      "Next": 4,
      "Prallel": -1
    },
    {
      "Node": "{ \"NpcTransformAction\" : True, { 112.16200, 2.18500, -792.69900} , True, { 0.00000, 264.01850, 0.00000} , \"in0109\"} ",
      "Next": 22,
      "Prallel": -1
    },
    {
      "Node": "{ \"PlayerTransformAction\" : True, { 113.21200, 2.64037, -795.02700} , True, { 0.00000, 332.00610, 0.00000} } ",
      "Next": 7,
      "Prallel": -1
    },
    {
      "Node": "{ \"PlayNpcAnimationAction\" : [ { 2, \"f_sit01_await00\", 1.00000}  ], \"in0109\"} ",
      "Next": 96,
      "Prallel": -1
    },
    {
      "Node": "{ \"PlayPlayerAnimationAction\" : [ { 2, \"m_sit60_await00\", 1.00000}  ]} ",
      "Next": 6,
      "Prallel": -1
    },
    {
      "Node": "{ \"BranchAction\" : { \"LogicalNode\" : [ { \"CheckFlag\" : 1, 3, \"fe1010904_2_03\"}  ], 0} , 9, 11} ",
      "Next": -1,
      "Prallel": -1
    },
    {
      "Node": "{ \"TimerAction\" : 2.00000} ",
      "Next": 10,
      "Prallel": 13
    },
    {
      "Node": "{ \"ScreenFadeAction\" : True, 5.00000} ",
      "Next": 17,
      "Prallel": -1
    },
    {
      "Node": "{ \"TimerAction\" : 0.50000} ",
      "Next": 12,
      "Prallel": 14
    },
    {
      "Node": "{ \"ScreenFadeAction\" : True, 1.00000} ",
      "Next": 15,
      "Prallel": -1
    },
    {
      "Node": "{ \"PlayNpcAnimationAction\" : [ { 0, \"m_stand00_await08\", 1.00000}  ], \"in0701\"} ",
      "Next": -1,
      "Prallel": -1
    },
    {
      "Node": "{ \"PlayNpcAnimationAction\" : [ { 0, \"m_stand00_await08\", 1.00000}  ], \"in0701\"} ",
      "Next": -1,
      "Prallel": -1
    },
    {
      "Node": "{ \"TimerAction\" : 2.00000} ",
      "Next": 16,
      "Prallel": -1
    },
    {
      "Node": "{ \"TalkAction\" : \"t1010904_119\"} ",
      "Next": 18,
      "Prallel": -1
    },
    {
      "Node": "{ \"TimerAction\" : 1.00000} ",
      "Next": 16,
      "Prallel": -1
    },
    {
      "Node": "{ \"TimerAction\" : 0.50000} ",
      "Next": 19,
      "Prallel": -1
    },
    {
      "Node": "{ \"TalkAction\" : \"t1010904_121\"} ",
      "Next": 30,
      "Prallel": -1
    },
    {
      "Node": "{ \"CameraTransformAction\" : True, { 109.94430, 2.99512, -796.92050} , 0.00000, True, { 1.55155, 38.33621, 0.00039} , 0.00000, 45} ",
      "Next": 3,
      "Prallel": -1
    },
    {
      "Node": "{ \"EventCubeTransformAction\" : True, { 112.09300, 1.98300, -792.08600} , 0.00000, True, { 0.00000, 0.00000, 0.00000} , 0.00000, \"eb1010904_01\"} ",
      "Next": 20,
      "Prallel": -1
    },
    {
      "Node": "{ \"BranchAction\" : { \"LogicalNode\" : [ { \"CheckFlag\" : 1, 3, \"fe1010904_2_03\"}  ], 0} , 5, 23} ",
      "Next": -1,
      "Prallel": -1
    },
    {
      "Node": "{ \"PlayerTransformAction\" : True, { 112.82900, 1.81000, -794.30200} , True, { 0.00000, 317.55260, 0.00000} } ",
      "Next": 6,
      "Prallel": -1
    },
    {
      "Node": "{ \"PlayPlayerAnimationAction\" : [ { 0, \"m_sit60_stop00\", 1.00000}  ]} ",
      "Next": 27,
      "Prallel": 26
    },
    {
      "Node": "{ \"BranchAction\" : { \"LogicalNode\" : [ { \"CheckFlag\" : 1, 3, \"fe1010904_2_03\"}  ], 0} , 24, 31} ",
      "Next": -1,
      "Prallel": -1
    },
    {
      "Node": "{ \"ScreenFadeAction\" : False, 0.50000} ",
      "Next": -1,
      "Prallel": -1
    },
    {
      "Node": "{ \"PlayerTransformAction\" : True, { 112.82900, 1.81000, -794.30200} , True, { 0.00000, 317.55260, 0.00000} } ",
      "Next": 29,
      "Prallel": -1
    },
    {
      "Node": "{ \"ScreenFadeAction\" : True, 0.50000} ",
      "Next": 31,
      "Prallel": -1
    },
    {
      "Node": "{ \"TimerAction\" : 0.30000} ",
      "Next": 28,
      "Prallel": -1
    },
    {
      "Node": "{ \"NpcSimpleTransformAction\" : False, { 110.98300, 1.81954, -792.48000} , 0.00000, True, { 0.00000, 138.65040, 0.00000} , \"in0701\"} ",
      "Next": 32,
      "Prallel": -1
    },
    {
      "Node": "{ \"PlayPlayerAnimationAction\" : [ { 0, \"m_stand00_talk02\", 1.00000}  ]} ",
      "Next": 35,
      "Prallel": -1
    },
    {
      "Node": "{ \"BranchAction\" : { \"LogicalNode\" : [ { \"CheckFlag\" : 1, 1, \"fe1010904_2_04\"}  ], 0} , 33, 34} ",
      "Next": -1,
      "Prallel": -1
    },
    {
      "Node": "{ \"TalkAction\" : \"t1010904_132\"} ",
      "Next": 25,
      "Prallel": -1
    },
    {
      "Node": "{ \"TalkAction\" : \"t1010904_126\"} ",
      "Next": 25,
      "Prallel": -1
    },
    {
      "Node": "{ \"BranchAction\" : { \"LogicalNode\" : [ { \"CheckFlag\" : 1, 1, \"fe1010904_2_04\"}  ], 0} , 36, 37} ",
      "Next": -1,
      "Prallel": -1
    },
    {
      "Node": "{ \"TalkAction\" : \"t1010904_133\"} ",
      "Next": 38,
      "Prallel": -1
    },
    {
      "Node": "{ \"TalkAction\" : \"t1010904_127\"} ",
      "Next": 39,
      "Prallel": -1
    },
    {
      "Node": "{ \"NpcSimpleTransformAction\" : False, { 110.98300, 1.81954, -792.48000} , 0.00000, True, { 0.00000, 103.82610, 0.00000} , \"in0701\"} ",
      "Next": 40,
      "Prallel": -1
    },
    {
      "Node": "{ \"NpcSimpleTransformAction\" : False, { 110.98300, 1.81954, -792.48000} , 0.00000, True, { 0.00000, 103.82610, 0.00000} , \"in0701\"} ",
      "Next": 41,
      "Prallel": -1
    },
    {
      "Node": "{ \"TalkAction\" : \"t1010904_136\"} ",
      "Next": 42,
      "Prallel": -1
    },
    {
      "Node": "{ \"TalkAction\" : \"t1010904_130\"} ",
      "Next": 42,
      "Prallel": -1
    },
    {
      "Node": "{ \"NpcSimpleTransformAction\" : False, { 110.98300, 1.81954, -792.48000} , 0.00000, True, { 0.00000, 138.65040, 0.00000} , \"in0701\"} ",
      "Next": 43,
      "Prallel": -1
    },
    {
      "Node": "{ \"PlayPlayerAnimationAction\" : [ { 0, \"m_stand00_talk02\", 1.00000}  ]} ",
      "Next": 44,
      "Prallel": -1
    },
    {
      "Node": "{ \"TalkAction\" : \"t1010904_144\"} ",
      "Next": 45,
      "Prallel": -1
    },
    {
      "Node": "{ \"TimerAction\" : 1.00000} ",
      "Next": 46,
      "Prallel": -1
    },
    {
      "Node": "{ \"TalkAction\" : \"t1010904_146\"} ",
      "Next": 47,
      "Prallel": -1
    },
    {
      "Node": "{ \"NpcSimpleTransformAction\" : False, { 110.98300, 1.81954, -792.48000} , 0.00000, True, { 0.00000, 103.82610, 0.00000} , \"in0701\"} ",
      "Next": 48,
      "Prallel": -1
    },
    {
      "Node": "{ \"TalkAction\" : \"t1010904_147\"} ",
      "Next": 94,
      "Prallel": -1
    },
    {
      "Node": "{ \"ScreenFadeAction\" : False, 0.40000} ",
      "Next": 52,
      "Prallel": -1
    },
    {
      "Node": "{ \"NpcTransformAction\" : True, { 112.01600, 1.80100, -792.82400} , True, { 0.00000, 264.01850, 0.00000} , \"in0109\"} ",
      "Next": 93,
      "Prallel": -1
    },
    {
      "Node": "{ \"EventCubeTransformAction\" : True, { 0.00000, 0.00000, 0.00000} , 0.00000, True, { 0.00000, 0.00000, 0.00000} , 0.00000, \"eb1010904_01\"} ",
      "Next": 50,
      "Prallel": -1
    },
    {
      "Node": "{ \"TimerAction\" : 0.30000} ",
      "Next": 51,
      "Prallel": -1
    },
    {
      "Node": "{ \"TimerAction\" : 0.30000} ",
      "Next": 54,
      "Prallel": -1
    },
    {
      "Node": "{ \"ScreenFadeAction\" : True, 0.40000} ",
      "Next": 55,
      "Prallel": -1
    },
    {
      "Node": "{ \"NpcSimpleTransformAction\" : False, { 112.01600, 1.80100, -792.82400} , 0.00000, True, { 0.00000, 168.21470, 0.00000} , \"in0109\"} ",
      "Next": 56,
      "Prallel": -1
    },
    {
      "Node": "{ \"TalkAction\" : \"t1010904_150\"} ",
      "Next": 61,
      "Prallel": 57
    },
    {
      "Node": "{ \"NpcSimpleTransformAction\" : False, { 110.98300, 1.81954, -792.48000} , 0.00000, True, { 0.00000, 138.65040, 0.00000} , \"in0701\"} ",
      "Next": -1,
      "Prallel": -1
    },
    {
      "Node": "{ \"NpcSimpleTransformAction\" : False, { 112.01600, 1.80100, -792.82400} , 0.00000, True, { 0.00000, 264.01850, 0.00000} , \"in0109\"} ",
      "Next": 60,
      "Prallel": -1
    },
    {
      "Node": "{ \"NpcSimpleTransformAction\" : False, { 110.98300, 1.81954, -792.48000} , 0.00000, True, { 0.00000, 103.82610, 0.00000} , \"in0701\"} ",
      "Next": -1,
      "Prallel": -1
    },
    {
      "Node": "{ \"TalkAction\" : \"t1010904_168\"} ",
      "Next": 64,
      "Prallel": 59
    },
    {
      "Node": "{ \"TimerAction\" : 1.00000} ",
      "Next": 62,
      "Prallel": -1
    },
    {
      "Node": "{ \"TalkAction\" : \"t1010904_169\"} ",
      "Next": 63,
      "Prallel": -1
    },
    {
      "Node": "{ \"TimerAction\" : 0.50000} ",
      "Next": 58,
      "Prallel": -1
    },
    {
      "Node": "{ \"ScreenFadeAction\" : False, 0.50000} ",
      "Next": 66,
      "Prallel": -1
    },
    {
      "Node": "{ \"NpcTransformAction\" : True, { 0.00000, 0.00000, 0.00000} , False, { 0.00000, 0.00000, 0.00000} , \"in0109\"} ",
      "Next": 69,
      "Prallel": -1
    },
    {
      "Node": "{ \"TimerAction\" : 0.50000} ",
      "Next": 65,
      "Prallel": -1
    },
    {
      "Node": "{ \"TimerAction\" : 0.50000} ",
      "Next": 68,
      "Prallel": -1
    },
    {
      "Node": "{ \"ScreenFadeAction\" : True, 1.00000} ",
      "Next": 71,
      "Prallel": -1
    },
    {
      "Node": "{ \"NpcSimpleTransformAction\" : False, { 110.98300, 1.81954, -792.48000} , 0.00000, True, { 0.00000, 175.54690, 0.00000} , \"in0701\"} ",
      "Next": 67,
      "Prallel": -1
    },
    {
      "Node": "{ \"NpcSimpleTransformAction\" : False, { 110.98300, 1.81954, -792.48000} , 0.00000, True, { 0.00000, 138.65040, 0.00000} , \"in0701\"} ",
      "Next": 72,
      "Prallel": -1
    },
    {
      "Node": "{ \"TimerAction\" : 0.50000} ",
      "Next": 78,
      "Prallel": -1
    },
    {
      "Node": "{ \"TalkAction\" : \"t1010904_172\"} ",
      "Next": 73,
      "Prallel": -1
    },
    {
      "Node": "{ \"TimerAction\" : 0.50000} ",
      "Next": 74,
      "Prallel": -1
    },
    {
      "Node": "{ \"TalkAction\" : \"t1010904_175\"} ",
      "Next": 75,
      "Prallel": -1
    },
    {
      "Node": "{ \"TimerAction\" : 0.30000} ",
      "Next": 76,
      "Prallel": -1
    },
    {
      "Node": "{ \"TalkAction\" : \"t1010904_176\"} ",
      "Next": 77,
      "Prallel": -1
    },
    {
      "Node": "{ \"ScreenFadeAction\" : False, 1.50000} ",
      "Next": 86,
      "Prallel": -1
    },
    {
      "Node": "{ \"BranchAction\" : { \"LogicalNode\" : [ { \"CheckFlag\" : 0, 3, \"fe1010904_2_02\"}  ], 0} , 79, 70} ",
      "Next": -1,
      "Prallel": -1
    },
    {
      "Node": "{ \"TalkAction\" : \"t1010904_177\"} ",
      "Next": 80,
      "Prallel": -1
    },
    {
      "Node": "{ \"TimerAction\" : 0.50000} ",
      "Next": 81,
      "Prallel": -1
    },
    {
      "Node": "{ \"NpcSimpleTransformAction\" : False, { 110.98300, 1.81954, -792.48000} , 0.00000, True, { 0.00000, 138.65040, 0.00000} , \"in0701\"} ",
      "Next": 82,
      "Prallel": -1
    },
    {
      "Node": "{ \"TalkAction\" : \"t1010904_178\"} ",
      "Next": 83,
      "Prallel": -1
    },
    {
      "Node": "{ \"TimerAction\" : 0.30000} ",
      "Next": 84,
      "Prallel": -1
    },
    {
      "Node": "{ \"TalkAction\" : \"t1010904_179\"} ",
      "Next": 85,
      "Prallel": -1
    },
    {
      "Node": "{ \"ScreenFadeAction\" : False, 0.50000} ",
      "Next": 86,
      "Prallel": -1
    },
    {
      "Node": "{ \"TimerAction\" : 0.30000} ",
      "Next": 87,
      "Prallel": -1
    },
    {
      "Node": "{ \"TalkAction\" : \"t1010904_185\"} ",
      "Next": 95,
      "Prallel": -1
    },
    {
      "Node": "{ \"TimerAction\" : 2.00000} ",
      "Next": 89,
      "Prallel": 98
    },
    {
      "Node": "{ \"BranchAction\" : { \"LogicalNode\" : [ { \"CheckCurrentTime\" : 1}  ], 0} , 90, 91} ",
      "Next": -1,
      "Prallel": -1
    },
    {
      "Node": "{ \"LoadScenesAction\" : \"S0202\", { 0.00000, 0.00000, 0.00000} , { 0.00000, 0.00000, 0.00000} , 0, True, 0, \"\", 1.00000} ",
      "Next": -1,
      "Prallel": -1
    },
    {
      "Node": "{ \"LoadScenesAction\" : \"S0202\", { 0.00000, 0.00000, 0.00000} , { 0.00000, 0.00000, 0.00000} , 0, False, 1, \"\", 1.00000} ",
      "Next": -1,
      "Prallel": -1
    },
    {
      "Node": "{ \"PlayNpcAnimationAction\" : [ { 2, \"f_stand07_await00\", 1.00000}  ], \"in0109\"} ",
      "Next": 53,
      "Prallel": -1
    },
    {
      "Node": "{ \"SetNpcAnimationAction\" : \"in0109_g75\", \"f_stand07_await00\", False} ",
      "Next": 92,
      "Prallel": -1
    },
    {
      "Node": "{ \"TimerAction\" : 0.30000} ",
      "Next": 49,
      "Prallel": -1
    },
    {
      "Node": "{ \"SetFlagAction\" : 0, 2, \"fe1010904_2_01\"} ",
      "Next": 88,
      "Prallel": -1
    },
    {
      "Node": "{ \"NpcWeaponActiveAction\" : False, \"in0109\"} ",
      "Next": 97,
      "Prallel": -1
    },
    {
      "Node": "{ \"PlayerWeaponActiveAction\" : False} ",
      "Next": 8,
      "Prallel": -1
    },
    {
      "Node": "{ \"MusicAction\" : \"\", 0.00000, False, 0.00000, True, 1.50000} ",
      "Next": -1,
      "Prallel": -1
    }
  ],
  "Name": "净四阶在百草芦"
}