{
  "EntryIndex": 0,
  "Nodes": [
    {
      "Node": "{ \"TimerAction\" : 0.50000} ",
      "Next": 1,
      "Prallel": -1
    },
    {
      "Node": "{ \"LoadScenesAction\" : \"S0108\", { 0.00000, 0.00000, 0.00000} , { 0.00000, 0.00000, 0.00000} , 0, False, 0} ",
      "Next": 6,
      "Prallel": -1
    },
    {
      "Node": "{ \"PlayerTransformAction\" : True, { -1371.45700, 8.58778, 692.71400} , True, { 0.00000, 299.10990, 0.00000} } ",
      "Next": 3,
      "Prallel": -1
    },
    {
      "Node": "{ \"NpcTransformAction\" : True, { -1379.80000, 8.58778, 694.01000} , True, { 0.00000, 283.94590, 0.00000} , \"in0105\"} ",
      "Next": 4,
      "Prallel": -1
    },
    {
      "Node": "{ \"PlayNpcAnimationAction\" : [ { 2, \"in0105_empty_idle00\", 1.00000}  ], \"in0105\"} ",
      "Next": 5,
      "Prallel": -1
    },
    {
      "Node": "{ \"TimerAction\" : 0.50000} ",
      "Next": 7,
      "Prallel": -1
    },
    {
      "Node": "{ \"CameraTransformAction\" : True, { -1371.31600, 11.25978, 688.56790} , 0.00000, True, { 17.08110, 323.53720, 0.00000} , 0.00000, 45} ",
      "Next": 2,
      "Prallel": -1
    },
    {
      "Node": "{ \"ScreenFadeAction\" : True, 1.50000} ",
      "Next": 11,
      "Prallel": 8
    },
    {
      "Node": "{ \"PlayerSimpleTransformAction\" : True, { -1373.18600, 8.58778, 692.93000} , 3.00000, True, { 0.00000, 299.16160, 0.00000} } ",
      "Next": -1,
      "Prallel": 9
    },
    {
      "Node": "{ \"TimerAction\" : 1.00000} ",
      "Next": 10,
      "Prallel": -1
    },
    {
      "Node": "{ \"PlayNpcAnimationAction\" : [ { 0, \"skill_MA0905_b02\", 1.00000} , { 2, \"in0105_empty_idle00\", 1.00000}  ], \"in0105\"} ",
      "Next": -1,
      "Prallel": -1
    },
    {
      "Node": "{ \"TimerAction\" : 2.00000} ",
      "Next": 12,
      "Prallel": -1
    },
    {
      "Node": "{ \"TalkAction\" : \"t1010500_002\"} ",
      "Next": 13,
      "Prallel": -1
    },
    {
      "Node": "{ \"ScreenFadeAction\" : False, 2.00000} ",
      "Next": 14,
      "Prallel": -1
    },
    {
      "Node": "{ \"TimerAction\" : 1.00000} ",
      "Next": 15,
      "Prallel": -1
    },
    {
      "Node": "{ \"LoadScenesAction\" : \"S0202\", { 0.00000, 0.00000, 0.00000} , { 0.00000, 0.00000, 0.00000} , 0, False, 0} ",
      "Next": -1,
      "Prallel": -1
    }
  ],
  "Name": "m605in010520_00：石崑三階（目前先將玩家丟回宿舍）"
}