{
  "Id": "bs1312501_11a",
  "Name": "bs1312501_11a",
  "Infos": [
    {
      "Index": 0,
      "Node": "{ \"BattleEventNode\" : 100, 0, [ ]} ",
      "Next": 1,
      "Prallel": -1,
      "Child": [
        1,
        2
      ]
    },
    {
      "Index": 1,
      "Node": "{ \"BattleResultAddUnit\" : \"Player\", 0, 102202200, 1.00000, 0.00000} ",
      "Next": 2,
      "Prallel": -1,
      "Child": []
    },
    {
      "Index": 2,
      "Node": "{ \"BattleResultAddUnit\" : \"in0202\", 1, 202102200, 1.00000, 0.00000} ",
      "Next": -1,
      "Prallel": -1,
      "Child": []
    },
    {
      "Index": 3,
      "Node": "{ \"BattleEventNode\" : 200, 0, [ ]} ",
      "Next": 5,
      "Prallel": -1,
      "Child": [
        5
      ]
    },
    {
      "Index": 4,
      "Node": "{ \"BattleFactorTurn\" : 1, 0} ",
      "Next": 6,
      "Prallel": -1,
      "Child": []
    },
    {
      "Index": 5,
      "Node": "{ \"StepByStepNode\" : [ ]} ",
      "Next": 4,
      "Prallel": -1,
      "Child": [
        4,
        6,
        7
      ]
    },
    {
      "Index": 6,
      "Node": "{ \"ExecuteOnceNode\" } ",
      "Next": 7,
      "Prallel": -1,
      "Child": []
    },
    {
      "Index": 7,
      "Node": "{ \"BattleResultTalk\" : \"t1312530_100\"} ",
      "Next": -1,
      "Prallel": -1,
      "Child": []
    },
    {
      "Index": 8,
      "Node": "{ \"BattleEventNode\" : 400, 0, [ ]} ",
      "Next": 10,
      "Prallel": -1,
      "Child": [
        10
      ]
    },
    {
      "Index": 9,
      "Node": "{ \"BattleFactorTargetDestroy\" : \"in0202\"} ",
      "Next": 11,
      "Prallel": -1,
      "Child": []
    },
    {
      "Index": 10,
      "Node": "{ \"StepByStepNode\" : [ ]} ",
      "Next": 9,
      "Prallel": -1,
      "Child": [
        9,
        11,
        12,
        13
      ]
    },
    {
      "Index": 11,
      "Node": "{ \"ExecuteOnceNode\" } ",
      "Next": 12,
      "Prallel": -1,
      "Child": []
    },
    {
      "Index": 12,
      "Node": "{ \"BattleResultTalk\" : \"t1312530_104\"} ",
      "Next": 13,
      "Prallel": -1,
      "Child": []
    },
    {
      "Index": 13,
      "Node": "{ \"BattleResultWin\" : \"\"} ",
      "Next": -1,
      "Prallel": -1,
      "Child": []
    },
    {
      "Index": 14,
      "Node": "{ \"BattleEventNode\" : 400, 0, [ ]} ",
      "Next": 16,
      "Prallel": -1,
      "Child": [
        16
      ]
    },
    {
      "Index": 15,
      "Node": "{ \"BattleFactorTargetDestroy\" : \"Player\"} ",
      "Next": 17,
      "Prallel": -1,
      "Child": []
    },
    {
      "Index": 16,
      "Node": "{ \"StepByStepNode\" : [ ]} ",
      "Next": 15,
      "Prallel": -1,
      "Child": [
        15,
        17,
        18,
        19
      ]
    },
    {
      "Index": 17,
      "Node": "{ \"ExecuteOnceNode\" } ",
      "Next": 18,
      "Prallel": -1,
      "Child": []
    },
    {
      "Index": 18,
      "Node": "{ \"BattleResultTalk\" : \"t1312530_148\"} ",
      "Next": 19,
      "Prallel": -1,
      "Child": []
    },
    {
      "Index": 19,
      "Node": "{ \"BattleResultLose\" : \"\"} ",
      "Next": -1,
      "Prallel": -1,
      "Child": []
    },
    {
      "Index": 20,
      "Node": "{ \"BattleEventNode\" : 200, 0, [ ]} ",
      "Next": 22,
      "Prallel": -1,
      "Child": [
        22
      ]
    },
    {
      "Index": 21,
      "Node": "{ \"BattleFactorTurn\" : 1, 2} ",
      "Next": 25,
      "Prallel": -1,
      "Child": []
    },
    {
      "Index": 22,
      "Node": "{ \"StepByStepNode\" : [ ]} ",
      "Next": 21,
      "Prallel": -1,
      "Child": [
        21,
        25,
        23,
        24,
        26,
        27,
        28
      ]
    },
    {
      "Index": 23,
      "Node": "{ \"ExecuteOnceNode\" } ",
      "Next": 24,
      "Prallel": -1,
      "Child": []
    },
    {
      "Index": 24,
      "Node": "{ \"BattleResultTalk\" : \"t1312530_108\"} ",
      "Next": 26,
      "Prallel": -1,
      "Child": []
    },
    {
      "Index": 25,
      "Node": "{ \"BattleFactorGlobalFlag\" : 1, 1, \"fe1010207_2_07\", \"段红儿=恋人\"} ",
      "Next": 23,
      "Prallel": -1,
      "Child": []
    },
    {
      "Index": 26,
      "Node": "{ \"BattleResultAddUnit\" : \"in0102\", 0, 104204200, 1.00000, 0.00000} ",
      "Next": 27,
      "Prallel": -1,
      "Child": []
    },
    {
      "Index": 27,
      "Node": "{ \"BattleResultAddBuff\" : True, \"in0102\", \"\", True} ",
      "Next": 28,
      "Prallel": -1,
      "Child": []
    },
    {
      "Index": 28,
      "Node": "{ \"BattleResultTalk\" : \"t1312530_112\"} ",
      "Next": -1,
      "Prallel": -1,
      "Child": []
    },
    {
      "Index": 29,
      "Node": "{ \"BattleEventNode\" : 200, 0, [ ]} ",
      "Next": 31,
      "Prallel": -1,
      "Child": [
        31
      ]
    },
    {
      "Index": 30,
      "Node": "{ \"BattleFactorTurn\" : 1, 2} ",
      "Next": 32,
      "Prallel": -1,
      "Child": []
    },
    {
      "Index": 31,
      "Node": "{ \"StepByStepNode\" : [ ]} ",
      "Next": 30,
      "Prallel": -1,
      "Child": [
        30,
        32,
        33,
        34,
        35,
        36,
        37
      ]
    },
    {
      "Index": 32,
      "Node": "{ \"BattleFactorGlobalFlag\" : 1, 1, \"fe1010307_2_07\", \"锺若昕=恋人\"} ",
      "Next": 33,
      "Prallel": -1,
      "Child": []
    },
    {
      "Index": 33,
      "Node": "{ \"ExecuteOnceNode\" } ",
      "Next": 34,
      "Prallel": -1,
      "Child": []
    },
    {
      "Index": 34,
      "Node": "{ \"BattleResultTalk\" : \"t1312530_108\"} ",
      "Next": 35,
      "Prallel": -1,
      "Child": []
    },
    {
      "Index": 35,
      "Node": "{ \"BattleResultAddUnit\" : \"in0103\", 0, 104204200, 1.00000, 0.00000} ",
      "Next": 36,
      "Prallel": -1,
      "Child": []
    },
    {
      "Index": 36,
      "Node": "{ \"BattleResultAddBuff\" : True, \"in0103\", \"\", True} ",
      "Next": 37,
      "Prallel": -1,
      "Child": []
    },
    {
      "Index": 37,
      "Node": "{ \"BattleResultTalk\" : \"t1312530_112\"} ",
      "Next": -1,
      "Prallel": -1,
      "Child": []
    },
    {
      "Index": 38,
      "Node": "{ \"BattleEventNode\" : 200, 0, [ ]} ",
      "Next": 40,
      "Prallel": -1,
      "Child": [
        40
      ]
    },
    {
      "Index": 39,
      "Node": "{ \"BattleFactorTurn\" : 1, 2} ",
      "Next": 41,
      "Prallel": -1,
      "Child": []
    },
    {
      "Index": 40,
      "Node": "{ \"StepByStepNode\" : [ ]} ",
      "Next": 39,
      "Prallel": -1,
      "Child": [
        39,
        41,
        42,
        43,
        44,
        45,
        46
      ]
    },
    {
      "Index": 41,
      "Node": "{ \"BattleFactorGlobalFlag\" : 1, 4, \"fe1307201_2_01\", \"萧芊菱=恋人\"} ",
      "Next": 42,
      "Prallel": -1,
      "Child": []
    },
    {
      "Index": 42,
      "Node": "{ \"ExecuteOnceNode\" } ",
      "Next": 43,
      "Prallel": -1,
      "Child": []
    },
    {
      "Index": 43,
      "Node": "{ \"BattleResultTalk\" : \"t1312530_108\"} ",
      "Next": 44,
      "Prallel": -1,
      "Child": []
    },
    {
      "Index": 44,
      "Node": "{ \"BattleResultAddUnit\" : \"in0104\", 0, 104204200, 1.00000, 0.00000} ",
      "Next": 45,
      "Prallel": -1,
      "Child": []
    },
    {
      "Index": 45,
      "Node": "{ \"BattleResultAddBuff\" : True, \"in0104\", \"\", True} ",
      "Next": 46,
      "Prallel": -1,
      "Child": []
    },
    {
      "Index": 46,
      "Node": "{ \"BattleResultTalk\" : \"t1312530_112\"} ",
      "Next": -1,
      "Prallel": -1,
      "Child": []
    },
    {
      "Index": 47,
      "Node": "{ \"BattleEventNode\" : 200, 0, [ ]} ",
      "Next": 49,
      "Prallel": -1,
      "Child": [
        49
      ]
    },
    {
      "Index": 48,
      "Node": "{ \"BattleFactorTurn\" : 1, 2} ",
      "Next": 50,
      "Prallel": -1,
      "Child": []
    },
    {
      "Index": 49,
      "Node": "{ \"StepByStepNode\" : [ ]} ",
      "Next": 48,
      "Prallel": -1,
      "Child": [
        48,
        50,
        51,
        52,
        53,
        54,
        55
      ]
    },
    {
      "Index": 50,
      "Node": "{ \"BattleFactorGlobalFlag\" : 1, 1, \"fe1010507_2_03\", \"石崑=恋人\"} ",
      "Next": 51,
      "Prallel": -1,
      "Child": []
    },
    {
      "Index": 51,
      "Node": "{ \"ExecuteOnceNode\" } ",
      "Next": 52,
      "Prallel": -1,
      "Child": []
    },
    {
      "Index": 52,
      "Node": "{ \"BattleResultTalk\" : \"t1312530_108\"} ",
      "Next": 53,
      "Prallel": -1,
      "Child": []
    },
    {
      "Index": 53,
      "Node": "{ \"BattleResultAddUnit\" : \"in0105\", 0, 104204200, 1.00000, 0.00000} ",
      "Next": 54,
      "Prallel": -1,
      "Child": []
    },
    {
      "Index": 54,
      "Node": "{ \"BattleResultAddBuff\" : True, \"in0105\", \"\", True} ",
      "Next": 55,
      "Prallel": -1,
      "Child": []
    },
    {
      "Index": 55,
      "Node": "{ \"BattleResultTalk\" : \"t1312530_112\"} ",
      "Next": -1,
      "Prallel": -1,
      "Child": []
    },
    {
      "Index": 56,
      "Node": "{ \"BattleEventNode\" : 200, 0, [ ]} ",
      "Next": 58,
      "Prallel": -1,
      "Child": [
        58
      ]
    },
    {
      "Index": 57,
      "Node": "{ \"BattleFactorTurn\" : 1, 2} ",
      "Next": 59,
      "Prallel": -1,
      "Child": []
    },
    {
      "Index": 58,
      "Node": "{ \"StepByStepNode\" : [ ]} ",
      "Next": 57,
      "Prallel": -1,
      "Child": [
        57,
        59,
        60,
        61,
        62,
        63,
        64
      ]
    },
    {
      "Index": 59,
      "Node": "{ \"BattleFactorGlobalFlag\" : 1, 1, \"fe1010607_2_01\", \"南飞鍠=恋人\"} ",
      "Next": 60,
      "Prallel": -1,
      "Child": []
    },
    {
      "Index": 60,
      "Node": "{ \"ExecuteOnceNode\" } ",
      "Next": 61,
      "Prallel": -1,
      "Child": []
    },
    {
      "Index": 61,
      "Node": "{ \"BattleResultTalk\" : \"t1312530_108\"} ",
      "Next": 62,
      "Prallel": -1,
      "Child": []
    },
    {
      "Index": 62,
      "Node": "{ \"BattleResultAddUnit\" : \"in0106\", 0, 104204200, 1.00000, 0.00000} ",
      "Next": 63,
      "Prallel": -1,
      "Child": []
    },
    {
      "Index": 63,
      "Node": "{ \"BattleResultAddBuff\" : True, \"in0106\", \"\", True} ",
      "Next": 64,
      "Prallel": -1,
      "Child": []
    },
    {
      "Index": 64,
      "Node": "{ \"BattleResultTalk\" : \"t1312530_112\"} ",
      "Next": -1,
      "Prallel": -1,
      "Child": []
    },
    {
      "Index": 65,
      "Node": "{ \"BattleEventNode\" : 200, 0, [ ]} ",
      "Next": 67,
      "Prallel": -1,
      "Child": [
        67
      ]
    },
    {
      "Index": 66,
      "Node": "{ \"BattleFactorTurn\" : 1, 2} ",
      "Next": 68,
      "Prallel": -1,
      "Child": []
    },
    {
      "Index": 67,
      "Node": "{ \"StepByStepNode\" : [ ]} ",
      "Next": 66,
      "Prallel": -1,
      "Child": [
        66,
        68,
        69,
        70,
        71,
        72,
        73
      ]
    },
    {
      "Index": 68,
      "Node": "{ \"BattleFactorGlobalFlag\" : 1, 1, \"fe1010707_1_02\", \"程墉=恋人\"} ",
      "Next": 69,
      "Prallel": -1,
      "Child": []
    },
    {
      "Index": 69,
      "Node": "{ \"ExecuteOnceNode\" } ",
      "Next": 70,
      "Prallel": -1,
      "Child": []
    },
    {
      "Index": 70,
      "Node": "{ \"BattleResultTalk\" : \"t1312530_108\"} ",
      "Next": 71,
      "Prallel": -1,
      "Child": []
    },
    {
      "Index": 71,
      "Node": "{ \"BattleResultAddUnit\" : \"in0107\", 0, 104204200, 1.00000, 0.00000} ",
      "Next": 72,
      "Prallel": -1,
      "Child": []
    },
    {
      "Index": 72,
      "Node": "{ \"BattleResultAddBuff\" : True, \"in0107\", \"\", True} ",
      "Next": 73,
      "Prallel": -1,
      "Child": []
    },
    {
      "Index": 73,
      "Node": "{ \"BattleResultTalk\" : \"t1312530_112\"} ",
      "Next": -1,
      "Prallel": -1,
      "Child": []
    },
    {
      "Index": 74,
      "Node": "{ \"BattleEventNode\" : 200, 0, [ ]} ",
      "Next": 76,
      "Prallel": -1,
      "Child": [
        76
      ]
    },
    {
      "Index": 75,
      "Node": "{ \"BattleFactorTurn\" : 1, 2} ",
      "Next": 77,
      "Prallel": -1,
      "Child": []
    },
    {
      "Index": 76,
      "Node": "{ \"StepByStepNode\" : [ ]} ",
      "Next": 75,
      "Prallel": -1,
      "Child": [
        75,
        77,
        78,
        79,
        80,
        81,
        82
      ]
    },
    {
      "Index": 77,
      "Node": "{ \"BattleFactorGlobalFlag\" : 1, 2, \"fe1010907_2_03\", \"净=恋人\"} ",
      "Next": 78,
      "Prallel": -1,
      "Child": []
    },
    {
      "Index": 78,
      "Node": "{ \"ExecuteOnceNode\" } ",
      "Next": 79,
      "Prallel": -1,
      "Child": []
    },
    {
      "Index": 79,
      "Node": "{ \"BattleResultTalk\" : \"t1312530_108\"} ",
      "Next": 80,
      "Prallel": -1,
      "Child": []
    },
    {
      "Index": 80,
      "Node": "{ \"BattleResultAddUnit\" : \"in0109\", 0, 104204200, 1.00000, 0.00000} ",
      "Next": 81,
      "Prallel": -1,
      "Child": []
    },
    {
      "Index": 81,
      "Node": "{ \"BattleResultAddBuff\" : True, \"in0109\", \"\", True} ",
      "Next": 82,
      "Prallel": -1,
      "Child": []
    },
    {
      "Index": 82,
      "Node": "{ \"BattleResultTalk\" : \"t1312530_112\"} ",
      "Next": -1,
      "Prallel": -1,
      "Child": []
    },
    {
      "Index": 83,
      "Node": "{ \"BattleEventNode\" : 200, 0, [ ]} ",
      "Next": 85,
      "Prallel": -1,
      "Child": [
        85
      ]
    },
    {
      "Index": 84,
      "Node": "{ \"BattleFactorTurn\" : 1, 2} ",
      "Next": 86,
      "Prallel": -1,
      "Child": []
    },
    {
      "Index": 85,
      "Node": "{ \"StepByStepNode\" : [ ]} ",
      "Next": 84,
      "Prallel": -1,
      "Child": [
        84,
        86,
        87,
        88,
        89,
        90,
        91
      ]
    },
    {
      "Index": 86,
      "Node": "{ \"BattleFactorGlobalFlag\" : 1, 2, \"fe1011007_2_05\", \"上官煦=恋人\"} ",
      "Next": 87,
      "Prallel": -1,
      "Child": []
    },
    {
      "Index": 87,
      "Node": "{ \"ExecuteOnceNode\" } ",
      "Next": 88,
      "Prallel": -1,
      "Child": []
    },
    {
      "Index": 88,
      "Node": "{ \"BattleResultTalk\" : \"t1312530_108\"} ",
      "Next": 89,
      "Prallel": -1,
      "Child": []
    },
    {
      "Index": 89,
      "Node": "{ \"BattleResultAddUnit\" : \"in0110\", 0, 104204200, 1.00000, 0.00000} ",
      "Next": 90,
      "Prallel": -1,
      "Child": []
    },
    {
      "Index": 90,
      "Node": "{ \"BattleResultAddBuff\" : True, \"in0110\", \"\", True} ",
      "Next": 91,
      "Prallel": -1,
      "Child": []
    },
    {
      "Index": 91,
      "Node": "{ \"BattleResultTalk\" : \"t1312530_112\"} ",
      "Next": -1,
      "Prallel": -1,
      "Child": []
    },
    {
      "Index": 92,
      "Node": "{ \"BattleEventNode\" : 200, 0, [ ]} ",
      "Next": 94,
      "Prallel": -1,
      "Child": [
        94
      ]
    },
    {
      "Index": 93,
      "Node": "{ \"BattleFactorTurn\" : 1, 2} ",
      "Next": 95,
      "Prallel": -1,
      "Child": []
    },
    {
      "Index": 94,
      "Node": "{ \"StepByStepNode\" : [ ]} ",
      "Next": 93,
      "Prallel": -1,
      "Child": [
        93,
        95,
        96,
        97,
        98,
        99,
        100
      ]
    },
    {
      "Index": 95,
      "Node": "{ \"BattleFactorGlobalFlag\" : 1, 2, \"fe1011107_2_06\", \"武辙=恋人\"} ",
      "Next": 96,
      "Prallel": -1,
      "Child": []
    },
    {
      "Index": 96,
      "Node": "{ \"ExecuteOnceNode\" } ",
      "Next": 97,
      "Prallel": -1,
      "Child": []
    },
    {
      "Index": 97,
      "Node": "{ \"BattleResultTalk\" : \"t1312530_108\"} ",
      "Next": 98,
      "Prallel": -1,
      "Child": []
    },
    {
      "Index": 98,
      "Node": "{ \"BattleResultAddUnit\" : \"in0111\", 0, 104204200, 1.00000, 0.00000} ",
      "Next": 99,
      "Prallel": -1,
      "Child": []
    },
    {
      "Index": 99,
      "Node": "{ \"BattleResultAddBuff\" : True, \"in0111\", \"\", True} ",
      "Next": 100,
      "Prallel": -1,
      "Child": []
    },
    {
      "Index": 100,
      "Node": "{ \"BattleResultTalk\" : \"t1312530_112\"} ",
      "Next": -1,
      "Prallel": -1,
      "Child": []
    }
  ],
  "Remark": "合一战(单挑段霄烈)",
  "WinTip": "Defeat Duan Xiaolie!",
  "LoseTip": "{name_1}{name_2} is defeated。"
}