{
  "EntryIndex": 0,
  "Nodes": [
    {
      "Node": "{ \"TimerAction\" : 0.50000} ",
      "Next": 1,
      "Prallel": -1
    },
    {
      "Node": "{ \"CameraTransformAction\" : True, { 95.24423, 141.73850, -76.96020} , 0.00000, True, { 8.39716, 55.21314, 2.40603} , 0.00000, 45} ",
      "Next": 3,
      "Prallel": -1
    },
    {
      "Node": "{ \"NpcTransformAction\" : True, { 106.92940, 133.14410, -68.37605} , True, { 0.00000, 77.76421, 0.00000} , \"in0107\"} ",
      "Next": 7,
      "Prallel": -1
    },
    {
      "Node": "{ \"PlayerTransformAction\" : True, { 107.07700, 133.14410, -71.08700} , True, { 0.00000, 70.67075, 0.00000} } ",
      "Next": 2,
      "Prallel": -1
    },
    {
      "Node": "{ \"TimerAction\" : 4.00000} ",
      "Next": 5,
      "Prallel": -1
    },
    {
      "Node": "{ \"TalkAction\" : \"t1010705_100\"} ",
      "Next": 13,
      "Prallel": -1
    },
    {
      "Node": "{ \"ScreenFadeAction\" : True, 2.00000} ",
      "Next": 4,
      "Prallel": 9
    },
    {
      "Node": "{ \"NpcWeaponActiveAction\" : True, \"in0107\"} ",
      "Next": 8,
      "Prallel": -1
    },
    {
      "Node": "{ \"TimerAction\" : 0.50000} ",
      "Next": 6,
      "Prallel": -1
    },
    {
      "Node": "{ \"PlayerSimpleTransformAction\" : True, { 111.92000, 133.14410, -70.64000} , 4.00000, True, { 0.00000, 70.67075, 0.00000} } ",
      "Next": -1,
      "Prallel": 10
    },
    {
      "Node": "{ \"NpcSimpleTransformAction\" : True, { 111.77240, 133.14410, -67.92905} , 4.00000, True, { 0.00000, 101.05600, 0.00000} , \"in0107\"} ",
      "Next": -1,
      "Prallel": 11
    },
    {
      "Node": "{ \"TimerAction\" : 3.00000} ",
      "Next": 12,
      "Prallel": -1
    },
    {
      "Node": "{ \"CameraTransformAction\" : True, { 108.62810, 135.07540, -69.13639} , 5.00000, True, { 9.59874, 94.45477, 2.41405} , 5.00000, 45} ",
      "Next": -1,
      "Prallel": -1
    },
    {
      "Node": "{ \"TimerAction\" : 0.50000} ",
      "Next": 14,
      "Prallel": -1
    },
    {
      "Node": "{ \"ScreenFadeAction\" : False, 1.50000} ",
      "Next": 16,
      "Prallel": 15
    },
    {
      "Node": "{ \"NpcSimpleTransformAction\" : True, { 113.65600, 133.14410, -68.42000} , 2.00000, True, { 0.00000, 106.57180, 0.00000} , \"in0107\"} ",
      "Next": -1,
      "Prallel": -1
    },
    {
      "Node": "{ \"TimerAction\" : 1.00000} ",
      "Next": 17,
      "Prallel": -1
    },
    {
      "Node": "{ \"TalkAction\" : \"t1010705_105\"} ",
      "Next": 19,
      "Prallel": -1
    },
    {
      "Node": "{ \"CameraTransformAction\" : True, { 112.95080, 136.77170, -70.23856} , 0.00000, True, { 36.90024, 102.54410, 2.97696} , 0.00000, 45} ",
      "Next": 21,
      "Prallel": -1
    },
    {
      "Node": "{ \"SetFlagAction\" : 0, 1, \"fe1010705_2_01\"} ",
      "Next": 20,
      "Prallel": -1
    },
    {
      "Node": "{ \"SortOutDesignatedEventCubeAction\" : \"eb1010705_01\"} ",
      "Next": 18,
      "Prallel": -1
    },
    {
      "Node": "{ \"TimerAction\" : 2.00000} ",
      "Next": 22,
      "Prallel": 27
    },
    {
      "Node": "{ \"ScreenFadeAction\" : True, 1.50000} ",
      "Next": 23,
      "Prallel": -1
    },
    {
      "Node": "{ \"TalkAction\" : \"t1010705_106\"} ",
      "Next": 24,
      "Prallel": -1
    },
    {
      "Node": "{ \"TimerAction\" : 1.00000} ",
      "Next": 25,
      "Prallel": -1
    },
    {
      "Node": "{ \"ScreenFadeAction\" : False, 1.50000} ",
      "Next": 26,
      "Prallel": -1
    },
    {
      "Node": "{ \"TimerAction\" : 0.50000} ",
      "Next": 30,
      "Prallel": -1
    },
    {
      "Node": "{ \"SoundAction\" : 3, \"UISE_Tired01.wav\", 0.00000, 1.00000} ",
      "Next": -1,
      "Prallel": 29
    },
    {
      "Node": "{ \"SoundAction\" : 3, \"UISE_Door01.wav\", 0.00000, 0.00000} ",
      "Next": -1,
      "Prallel": -1
    },
    {
      "Node": "{ \"TimerAction\" : 0.50000} ",
      "Next": 28,
      "Prallel": -1
    },
    {
      "Node": "{ \"LoadScenesAction\" : \"S1103\", { 0.00000, 0.00000, 0.00000} , { 0.00000, 0.00000, 0.00000} , 0, False, 0} ",
      "Next": 31,
      "Prallel": -1
    },
    {
      "Node": "{ \"RunCinematicAction\" : \"m605in010740_04\"} ",
      "Next": -1,
      "Prallel": -1
    }
  ],
  "Name": "m605in010740_03：來到瀑布旁"
}