{
  "EntryIndex": 0,
  "Nodes": [
    {
      "Node": "{ \"PlayerLocateAction\" : { 0.40000, -199.90000, 0.50000} , { 0.00000, 320.00000, 0.00000} } ",
      "Next": 1,
      "Prallel": -1
    },
    {
      "Node": "{ \"PlayerWeaponActiveAction\" : False} ",
      "Next": 88,
      "Prallel": -1
    },
    {
      "Node": "{ \"BranchAction\" : { \"LogicalNode\" : [ { \"Probability\" : 30.00000} , { \"CheckFlag\" : 1, 0, \"fe5305101_2_01\"}  ], 0} , 98, 124} ",
      "Next": -1,
      "Prallel": -1
    },
    {
      "Node": "{ \"NpcLocateAction\" : { 1.03000, -199.90000, 0.03000} , { 0.00000, 180.01900, 0.00000} , \"in0104\"} ",
      "Next": 5,
      "Prallel": -1
    },
    {
      "Node": "{ \"PlayerLocateAction\" : { -1.26600, -199.90000, 1.12600} , { 0.00000, 149.68330, 0.00000} } ",
      "Next": 3,
      "Prallel": -1
    },
    {
      "Node": "{ \"NurturanceChangeBackground\" : \"M01_08_2D\"} ",
      "Next": 6,
      "Prallel": -1
    },
    {
      "Node": "{ \"PlayPlayerAnimationAction\" : [ { 2, \"f_stand02_await00\", 1.00000}  ]} ",
      "Next": 7,
      "Prallel": -1
    },
    {
      "Node": "{ \"NurturanceTransitionsAction\" : False} ",
      "Next": 122,
      "Prallel": -1
    },
    {
      "Node": "{ \"NurturanceFadeAction\" : False, 0.50000} ",
      "Next": 34,
      "Prallel": -1
    },
    {
      "Node": "{ \"NurturanceTransitionsAction\" : True} ",
      "Next": 10,
      "Prallel": -1
    },
    {
      "Node": "{ \"SortOutDesignatedNpcAction\" : \"in0104\"} ",
      "Next": 11,
      "Prallel": -1
    },
    {
      "Node": "{ \"SortOutDesignatedEventCubeAction\" : \"eb6030101\"} ",
      "Next": 91,
      "Prallel": -1
    },
    {
      "Node": "{ \"BranchAction\" : { \"LogicalNode\" : [ { \"CheckCurrentTime\" : 1}  ], 0} , 13, 14} ",
      "Next": -1,
      "Prallel": -1
    },
    {
      "Node": "{ \"NurturanceLoadScenesAction\" : \"S0202\", { 0.00000, 0.00000, 0.00000} , { 0.00000, 0.00000, 0.00000} , 0, True, 0} ",
      "Next": -1,
      "Prallel": -1
    },
    {
      "Node": "{ \"NurturanceLoadScenesAction\" : \"S0202\", { 1499.94800, -0.00600, 758.87900} , { 0.00000, 0.00000, 0.00000} , 0, False, 1} ",
      "Next": -1,
      "Prallel": -1
    },
    {
      "Node": "{ \"BranchAction\" : { \"LogicalNode\" : [ { \"CheckFlag\" : 0, 0, \"fe6091100_1_01\"}  ], 0} , 16, 12} ",
      "Next": -1,
      "Prallel": -1
    },
    {
      "Node": "{ \"TalkAction\" : \"t6000000_067\"} ",
      "Next": 17,
      "Prallel": -1
    },
    {
      "Node": "{ \"RewardAction\" : \"re605in010400_00\"} ",
      "Next": 18,
      "Prallel": -1
    },
    {
      "Node": "{ \"SetFlagAction\" : 2, 1, \"fe6091100_1_01\"} ",
      "Next": 12,
      "Prallel": -1
    },
    {
      "Node": "{ \"NpcLocateAction\" : { 0.70000, -199.76000, 1.26000} , { 0.00000, 336.75060, 0.00000} , \"in0104\"} ",
      "Next": 120,
      "Prallel": -1
    },
    {
      "Node": "{ \"PlayerLocateAction\" : { 0.03000, -199.87100, 0.36000} , { 0.00000, 14.83069, 0.00000} } ",
      "Next": 19,
      "Prallel": -1
    },
    {
      "Node": "{ \"NurturanceChangeBackground\" : \"M01_04_2D\"} ",
      "Next": 22,
      "Prallel": -1
    },
    {
      "Node": "{ \"NurturanceTransitionsAction\" : False} ",
      "Next": 23,
      "Prallel": -1
    },
    {
      "Node": "{ \"TalkAction\" : \"t605in0104_120\"} ",
      "Next": 24,
      "Prallel": -1
    },
    {
      "Node": "{ \"NurturanceFadeAction\" : False, 0.50000} ",
      "Next": 36,
      "Prallel": -1
    },
    {
      "Node": "{ \"NurturanceTransitionsAction\" : True} ",
      "Next": 39,
      "Prallel": -1
    },
    {
      "Node": "{ \"SortOutDesignatedNpcAction\" : \"in0104\"} ",
      "Next": 38,
      "Prallel": -1
    },
    {
      "Node": "{ \"BranchAction\" : { \"LogicalNode\" : [ { \"CheckCurrentTime\" : 1}  ], 0} , 28, 29} ",
      "Next": -1,
      "Prallel": -1
    },
    {
      "Node": "{ \"NurturanceLoadScenesAction\" : \"S0202\", { 0.00000, 0.00000, 0.00000} , { 0.00000, 0.00000, 0.00000} , 0, True, 0} ",
      "Next": -1,
      "Prallel": -1
    },
    {
      "Node": "{ \"NurturanceLoadScenesAction\" : \"S0202\", { 1499.94800, -0.00600, 758.87900} , { 0.00000, 0.00000, 0.00000} , 0, False, 1} ",
      "Next": -1,
      "Prallel": -1
    },
    {
      "Node": "{ \"BranchAction\" : { \"LogicalNode\" : [ { \"CheckFlag\" : 0, 0, \"fe6091100_1_01\"}  ], 0} , 31, 27} ",
      "Next": -1,
      "Prallel": -1
    },
    {
      "Node": "{ \"TalkAction\" : \"t6000000_067\"} ",
      "Next": 32,
      "Prallel": -1
    },
    {
      "Node": "{ \"RewardAction\" : \"re605in010400_00\"} ",
      "Next": 33,
      "Prallel": -1
    },
    {
      "Node": "{ \"SetFlagAction\" : 2, 1, \"fe6091100_1_01\"} ",
      "Next": 27,
      "Prallel": -1
    },
    {
      "Node": "{ \"TimerAction\" : 0.50000} ",
      "Next": 9,
      "Prallel": -1
    },
    {
      "Node": "{ \"TalkAction\" : \"t605in0104_131\"} ",
      "Next": 8,
      "Prallel": -1
    },
    {
      "Node": "{ \"TimerAction\" : 0.50000} ",
      "Next": 37,
      "Prallel": -1
    },
    {
      "Node": "{ \"TalkAction\" : \"t605in0104_128\"} ",
      "Next": 25,
      "Prallel": -1
    },
    {
      "Node": "{ \"SortOutDesignatedEventCubeAction\" : \"eb6070101\"} ",
      "Next": 93,
      "Prallel": -1
    },
    {
      "Node": "{ \"PlayerChangeAccessoryAction\" : \"\"} ",
      "Next": 26,
      "Prallel": -1
    },
    {
      "Node": "{ \"NpcLocateAction\" : { 1.05000, -199.97500, 2.15000} , { 0.00000, 236.46630, 0.00000} , \"in0104\"} ",
      "Next": 42,
      "Prallel": -1
    },
    {
      "Node": "{ \"PlayerLocateAction\" : { -0.07000, -199.97500, 1.82000} , { 0.00000, 32.34473, 0.00000} } ",
      "Next": 40,
      "Prallel": -1
    },
    {
      "Node": "{ \"NurturanceChangeBackground\" : \"M01_05_2D\"} ",
      "Next": 46,
      "Prallel": -1
    },
    {
      "Node": "{ \"PlayPlayerAnimationAction\" : [ { 2, \"f_stand02_await00\", 1.00000}  ]} ",
      "Next": 125,
      "Prallel": -1
    },
    {
      "Node": "{ \"NurturanceTransitionsAction\" : False} ",
      "Next": 45,
      "Prallel": -1
    },
    {
      "Node": "{ \"TalkAction\" : \"t605in0104_149\"} ",
      "Next": 47,
      "Prallel": -1
    },
    {
      "Node": "{ \"EventCubeTransformAction\" : True, { 0.15000, -200.12000, 1.59000} , 0.00000, True, { 358.96360, 35.29793, 357.50080} , 0.00000, \"eb6060301\"} ",
      "Next": 43,
      "Prallel": -1
    },
    {
      "Node": "{ \"NurturanceFadeAction\" : False, 0.50000} ",
      "Next": 48,
      "Prallel": -1
    },
    {
      "Node": "{ \"TalkAction\" : \"t605in0104_160\"} ",
      "Next": 49,
      "Prallel": -1
    },
    {
      "Node": "{ \"EventCubeTransformAction\" : True, { 0.00000, 0.00000, 0.00000} , 0.00000, True, { 0.00000, 0.00000, 0.00000} , 0.00000, \"eb6060301\"} ",
      "Next": 51,
      "Prallel": -1
    },
    {
      "Node": "{ \"NpcLocateAction\" : { 0.60200, -199.90000, 1.91000} , { 0.00000, 298.11940, 0.00000} , \"in0104\"} ",
      "Next": 52,
      "Prallel": -1
    },
    {
      "Node": "{ \"PlayerLocateAction\" : { -0.44300, -199.96500, 2.13000} , { 0.00000, 117.55450, 0.00000} } ",
      "Next": 50,
      "Prallel": -1
    },
    {
      "Node": "{ \"NurturanceTransitionsAction\" : True} ",
      "Next": 55,
      "Prallel": -1
    },
    {
      "Node": "{ \"SortOutDesignatedNpcAction\" : \"in0104\"} ",
      "Next": 54,
      "Prallel": -1
    },
    {
      "Node": "{ \"SortOutDesignatedEventCubeAction\" : \"eb6060301\"} ",
      "Next": 89,
      "Prallel": -1
    },
    {
      "Node": "{ \"PlayerChangeAccessoryAction\" : \"\"} ",
      "Next": 53,
      "Prallel": -1
    },
    {
      "Node": "{ \"BranchAction\" : { \"LogicalNode\" : [ { \"CheckFlag\" : 0, 0, \"fe6091100_1_01\"}  ], 0} , 57, 59} ",
      "Next": -1,
      "Prallel": -1
    },
    {
      "Node": "{ \"TalkAction\" : \"t6000000_067\"} ",
      "Next": 58,
      "Prallel": -1
    },
    {
      "Node": "{ \"RewardAction\" : \"re605in010400_00\"} ",
      "Next": 62,
      "Prallel": -1
    },
    {
      "Node": "{ \"BranchAction\" : { \"LogicalNode\" : [ { \"CheckCurrentTime\" : 1}  ], 0} , 60, 61} ",
      "Next": -1,
      "Prallel": -1
    },
    {
      "Node": "{ \"NurturanceLoadScenesAction\" : \"S0202\", { 0.00000, 0.00000, 0.00000} , { 0.00000, 0.00000, 0.00000} , 0, True, 0} ",
      "Next": -1,
      "Prallel": -1
    },
    {
      "Node": "{ \"NurturanceLoadScenesAction\" : \"S0202\", { 1499.94800, -0.00600, 758.87900} , { 0.00000, 0.00000, 0.00000} , 0, False, 1} ",
      "Next": -1,
      "Prallel": -1
    },
    {
      "Node": "{ \"SetFlagAction\" : 2, 1, \"fe6091100_1_01\"} ",
      "Next": 59,
      "Prallel": -1
    },
    {
      "Node": "{ \"BranchAction\" : { \"LogicalNode\" : [ { \"CheckFlag\" : 1, 2, \"fe5305101_2_01\"} , { \"Probability\" : 50.00000}  ], 0} , 41, 2} ",
      "Next": -1,
      "Prallel": -1
    },
    {
      "Node": "{ \"NpcLocateAction\" : { 0.66700, -199.97500, 0.63800} , { 0.00000, 348.41890, 0.00000} , \"in0104\"} ",
      "Next": 71,
      "Prallel": -1
    },
    {
      "Node": "{ \"PlayerLocateAction\" : { -0.71300, -199.97500, 2.19400} , { 0.00000, 162.63210, 0.00000} } ",
      "Next": 64,
      "Prallel": -1
    },
    {
      "Node": "{ \"NurturanceChangeBackground\" : \"M06_01_2D\"} ",
      "Next": 68,
      "Prallel": -1
    },
    {
      "Node": "{ \"NpcLocateAction\" : { -0.35500, -199.97500, 1.07700} , { 0.00000, 29.52304, 0.00000} , \"in11034\"} ",
      "Next": 66,
      "Prallel": -1
    },
    {
      "Node": "{ \"PlayPlayerAnimationAction\" : [ { 2, \"f_stand02_await00\", 1.00000}  ]} ",
      "Next": 73,
      "Prallel": -1
    },
    {
      "Node": "{ \"NurturanceTransitionsAction\" : False} ",
      "Next": 70,
      "Prallel": -1
    },
    {
      "Node": "{ \"TalkAction\" : \"t605in0104_024\"} ",
      "Next": 75,
      "Prallel": 74
    },
    {
      "Node": "{ \"NpcWeaponActiveAction\" : True, \"in11034\"} ",
      "Next": 72,
      "Prallel": -1
    },
    {
      "Node": "{ \"NpcChangeWeaponPointAction\" : True, \"in11034\"} ",
      "Next": 67,
      "Prallel": -1
    },
    {
      "Node": "{ \"PlayNpcAnimationAction\" : [ { 2, \"m_single_idle00\", 1.00000}  ], \"in11034\"} ",
      "Next": 69,
      "Prallel": -1
    },
    {
      "Node": "{ \"PlayNpcAnimationAction\" : [ { 0, \"skill_MA0302_b01_neff\", 1.00000} , { 0, \"skill_MA0302_b01_neff\", 1.00000} , { 2, \"m_single_idle00\", 1.00000}  ], \"in11034\"} ",
      "Next": -1,
      "Prallel": -1
    },
    {
      "Node": "{ \"TalkAction\" : \"t605in0104_025\"} ",
      "Next": 76,
      "Prallel": -1
    },
    {
      "Node": "{ \"TalkAction\" : \"t605in0104_026\"} ",
      "Next": 77,
      "Prallel": -1
    },
    {
      "Node": "{ \"NurturanceFadeAction\" : False, 0.50000} ",
      "Next": 78,
      "Prallel": -1
    },
    {
      "Node": "{ \"TalkAction\" : \"t605in0104_047\"} ",
      "Next": 79,
      "Prallel": -1
    },
    {
      "Node": "{ \"SortOutDesignatedNpcAction\" : \"in0104,in11034\"} ",
      "Next": 80,
      "Prallel": -1
    },
    {
      "Node": "{ \"SortOutDesignatedEventCubeAction\" : \"eb6060301\"} ",
      "Next": 95,
      "Prallel": -1
    },
    {
      "Node": "{ \"BranchAction\" : { \"LogicalNode\" : [ { \"CheckFlag\" : 0, 0, \"fe6091100_1_01\"}  ], 0} , 82, 85} ",
      "Next": -1,
      "Prallel": -1
    },
    {
      "Node": "{ \"TalkAction\" : \"t6000000_067\"} ",
      "Next": 83,
      "Prallel": -1
    },
    {
      "Node": "{ \"RewardAction\" : \"re605in010400_00\"} ",
      "Next": 84,
      "Prallel": -1
    },
    {
      "Node": "{ \"SetFlagAction\" : 2, 1, \"fe6091100_1_01\"} ",
      "Next": 85,
      "Prallel": -1
    },
    {
      "Node": "{ \"BranchAction\" : { \"LogicalNode\" : [ { \"CheckCurrentTime\" : 1}  ], 0} , 86, 87} ",
      "Next": -1,
      "Prallel": -1
    },
    {
      "Node": "{ \"NurturanceLoadScenesAction\" : \"S0202\", { 0.00000, 0.00000, 0.00000} , { 0.00000, 0.00000, 0.00000} , 0, True, 0} ",
      "Next": -1,
      "Prallel": -1
    },
    {
      "Node": "{ \"NurturanceLoadScenesAction\" : \"S0202\", { 1499.94800, -0.00600, 758.87900} , { 0.00000, 0.00000, 0.00000} , 0, False, 1} ",
      "Next": -1,
      "Prallel": -1
    },
    {
      "Node": "{ \"TimerAction\" : 0.50000} ",
      "Next": 63,
      "Prallel": -1
    },
    {
      "Node": "{ \"PlayerWeaponActiveAction\" : False} ",
      "Next": 90,
      "Prallel": -1
    },
    {
      "Node": "{ \"NpcWeaponActiveAction\" : False, \"in11034\"} ",
      "Next": 56,
      "Prallel": -1
    },
    {
      "Node": "{ \"PlayerWeaponActiveAction\" : False} ",
      "Next": 92,
      "Prallel": -1
    },
    {
      "Node": "{ \"NpcWeaponActiveAction\" : False, \"in11034\"} ",
      "Next": 15,
      "Prallel": -1
    },
    {
      "Node": "{ \"PlayerWeaponActiveAction\" : False} ",
      "Next": 94,
      "Prallel": -1
    },
    {
      "Node": "{ \"NpcWeaponActiveAction\" : False, \"in11034\"} ",
      "Next": 30,
      "Prallel": -1
    },
    {
      "Node": "{ \"PlayerWeaponActiveAction\" : False} ",
      "Next": 96,
      "Prallel": -1
    },
    {
      "Node": "{ \"NpcWeaponActiveAction\" : False, \"in11034\"} ",
      "Next": 81,
      "Prallel": -1
    },
    {
      "Node": "{ \"NpcLocateAction\" : { 1.23000, -199.26000, -0.64000} , { 0.00000, 321.75690, 0.00000} , \"in0104\"} ",
      "Next": 99,
      "Prallel": -1
    },
    {
      "Node": "{ \"PlayerLocateAction\" : { -0.47200, -199.26900, 0.56800} , { 0.00000, 168.43380, 0.00000} } ",
      "Next": 97,
      "Prallel": -1
    },
    {
      "Node": "{ \"NurturanceChangeBackground\" : \"M06_04_2D\"} ",
      "Next": 100,
      "Prallel": -1
    },
    {
      "Node": "{ \"EventCubeTransformAction\" : True, { -0.75000, -199.85000, 0.72000} , 0.00000, True, { 0.00000, 136.49580, 359.29200} , 0.00000, \"eb6024101\"} ",
      "Next": 118,
      "Prallel": -1
    },
    {
      "Node": "{ \"PlayPlayerAnimationAction\" : [ { 2, \"m_sit81_await00\", 1.00000}  ]} ",
      "Next": 103,
      "Prallel": -1
    },
    {
      "Node": "{ \"NurturanceTransitionsAction\" : False} ",
      "Next": 104,
      "Prallel": -1
    },
    {
      "Node": "{ \"PlayNpcAnimationAction\" : [ { 2, \"m_sit81_await00\", 1.00000}  ], \"in0104\"} ",
      "Next": 102,
      "Prallel": -1
    },
    {
      "Node": "{ \"TalkAction\" : \"t605in0104_118\"} ",
      "Next": 105,
      "Prallel": -1
    },
    {
      "Node": "{ \"TimerAction\" : 0.50000} ",
      "Next": 106,
      "Prallel": -1
    },
    {
      "Node": "{ \"NurturanceTransitionsAction\" : True} ",
      "Next": 107,
      "Prallel": -1
    },
    {
      "Node": "{ \"SortOutDesignatedNpcAction\" : \"in0104\"} ",
      "Next": 108,
      "Prallel": -1
    },
    {
      "Node": "{ \"SortOutDesignatedEventCubeAction\" : \"eb6000014,eb6024101\"} ",
      "Next": 109,
      "Prallel": -1
    },
    {
      "Node": "{ \"PlayerWeaponActiveAction\" : False} ",
      "Next": 112,
      "Prallel": -1
    },
    {
      "Node": "{ \"BranchAction\" : { \"LogicalNode\" : [ { \"CheckFlag\" : 0, 0, \"fe6091100_1_01\"}  ], 0} , 111, 113} ",
      "Next": -1,
      "Prallel": -1
    },
    {
      "Node": "{ \"TalkAction\" : \"t6000000_067\"} ",
      "Next": 116,
      "Prallel": -1
    },
    {
      "Node": "{ \"NpcWeaponActiveAction\" : False, \"in11034\"} ",
      "Next": 110,
      "Prallel": -1
    },
    {
      "Node": "{ \"BranchAction\" : { \"LogicalNode\" : [ { \"CheckCurrentTime\" : 1}  ], 0} , 114, 115} ",
      "Next": -1,
      "Prallel": -1
    },
    {
      "Node": "{ \"NurturanceLoadScenesAction\" : \"S0202\", { 0.00000, 0.00000, 0.00000} , { 0.00000, 0.00000, 0.00000} , 0, True, 0} ",
      "Next": -1,
      "Prallel": -1
    },
    {
      "Node": "{ \"NurturanceLoadScenesAction\" : \"S0202\", { 1499.94800, -0.00600, 758.87900} , { 0.00000, 0.00000, 0.00000} , 0, False, 1} ",
      "Next": -1,
      "Prallel": -1
    },
    {
      "Node": "{ \"RewardAction\" : \"re605in010400_00\"} ",
      "Next": 117,
      "Prallel": -1
    },
    {
      "Node": "{ \"SetFlagAction\" : 2, 1, \"fe6091100_1_01\"} ",
      "Next": 113,
      "Prallel": -1
    },
    {
      "Node": "{ \"EventCubeTransformAction\" : True, { 1.32000, -199.85000, -0.89000} , 0.00000, True, { 0.00000, 136.49580, 359.29200} , 0.00000, \"eb6000014\"} ",
      "Next": 101,
      "Prallel": -1
    },
    {
      "Node": "{ \"EventCubeTransformAction\" : True, { 0.46700, -199.88300, 1.66000} , 0.00000, True, { 359.72020, 339.76850, 0.65040} , 0.00000, \"eb6070101\"} ",
      "Next": 21,
      "Prallel": -1
    },
    {
      "Node": "{ \"PlayPlayerAnimationAction\" : [ { 2, \"m_stand02_await00\", 1.00000}  ]} ",
      "Next": 121,
      "Prallel": -1
    },
    {
      "Node": "{ \"PlayNpcAnimationAction\" : [ { 2, \"f_sit06_await00\", 1.00000}  ], \"in0104\"} ",
      "Next": 119,
      "Prallel": -1
    },
    {
      "Node": "{ \"TimerAction\" : 1.50000} ",
      "Next": 123,
      "Prallel": -1
    },
    {
      "Node": "{ \"PlayerSimpleTransformAction\" : True, { -0.06000, -199.90000, -0.94000} , 2.50000, True, { 0.00000, 149.68330, 0.00000} } ",
      "Next": 35,
      "Prallel": -1
    },
    {
      "Node": "{ \"BranchAction\" : { \"LogicalNode\" : [ { \"Probability\" : 30.00000} , { \"CheckFlag\" : 1, 0, \"fe5305101_2_01\"}  ], 0} , 4, 20} ",
      "Next": -1,
      "Prallel": -1
    },
    {
      "Node": "{ \"TimerAction\" : 0.50000} ",
      "Next": 44,
      "Prallel": -1
    }
  ],
  "Name": ""
}